anki_ocr/__init__.py
anki_ocr/anki_ocr.py
anki_ocr-0.3.1.dist-info/LICENSE.md
anki_ocr-0.3.1.dist-info/METADATA
anki_ocr-0.3.1.dist-info/WHEEL
anki_ocr-0.3.1.dist-info/entry_points.txt
anki_ocr-0.3.1.dist-info/top_level.txt
anki_ocr-0.3.1.dist-info/RECORD
