Metadata-Version: 2.1
Name: anki-ocr
Version: 0.3.1
Summary: Converts physical flashcards to digital anki flashcards
Home-page: https://github.com/madelesi/anki_ocr
Author: madelesi
Author-email: saifemasoud@gmail.com
License: UNKNOWN
Platform: UNKNOWN
Classifier: Programming Language :: Python :: 3
Classifier: License :: OSI Approved :: MIT License
Classifier: Operating System :: OS Independent
Requires-Dist: genanki
